thewalrus/__init__.py
thewalrus/_hafnian.py
thewalrus/_hermite_multidimensional.py
thewalrus/_low_rank_haf.py
thewalrus/_montrealer.py
thewalrus/_permanent.py
thewalrus/_torontonian.py
thewalrus/_version.py
thewalrus/charpoly.py
thewalrus/csamples.py
thewalrus/decompositions.py
thewalrus/fock_gradients.py
thewalrus/grouped_click_probabilities.py
thewalrus/loop_hafnian_batch.py
thewalrus/loop_hafnian_batch_gamma.py
thewalrus/random.py
thewalrus/reference.py
thewalrus/samples.py
thewalrus/symplectic.py
thewalrus/quantum/__init__.py
thewalrus/quantum/adjacency_matrices.py
thewalrus/quantum/conversions.py
thewalrus/quantum/distinguishable_squeezers.py
thewalrus/quantum/entanglement.py
thewalrus/quantum/fock_tensors.py
thewalrus/quantum/gaussian_checks.py
thewalrus/quantum/means_and_variances.py
thewalrus/quantum/photon_number_distributions.py
thewalrus-0.21.0.dist-info/LICENSE
thewalrus-0.21.0.dist-info/METADATA
thewalrus-0.21.0.dist-info/WHEEL
thewalrus-0.21.0.dist-info/top_level.txt
thewalrus-0.21.0.dist-info/RECORD
