Metadata-Version: 2.1
Name: thewalrus
Version: 0.21.0
Summary: Open source library for hafnian calculation
Home-page: https://github.com/XanaduAI/thewalrus
Maintainer: Xanadu Inc.
Maintainer-email: software@xanadu.ai
License: Apache License 2.0
Classifier: Development Status :: 3 - Alpha
Classifier: Environment :: Console
Classifier: Intended Audience :: Science/Research
Classifier: License :: OSI Approved :: Apache Software License
Classifier: Natural Language :: English
Classifier: Operating System :: POSIX
Classifier: Operating System :: MacOS :: MacOS X
Classifier: Operating System :: POSIX :: Linux
Classifier: Operating System :: Microsoft :: Windows
Classifier: Programming Language :: Python
Classifier: Programming Language :: Python :: 3
Classifier: Programming Language :: Python :: 3.7
Classifier: Programming Language :: Python :: 3.8
Classifier: Programming Language :: Python :: 3.9
Classifier: Programming Language :: Python :: 3.10
Classifier: Programming Language :: Python :: 3 :: Only
Classifier: Topic :: Scientific/Engineering :: Physics
Provides: thewalrus
License-File: LICENSE
Requires-Dist: dask[delayed]
Requires-Dist: numba>=0.49.1
Requires-Dist: scipy>=1.2.1
Requires-Dist: sympy>=1.5.1
Requires-Dist: numpy>=1.19.2
